silkpy/__init__.py
silkpy/geometry_map.py
silkpy-0.0.1.dist-info/LICENSE
silkpy-0.0.1.dist-info/METADATA
silkpy-0.0.1.dist-info/WHEEL
silkpy-0.0.1.dist-info/top_level.txt
silkpy-0.0.1.dist-info/RECORD
